djconnectwise/__init__.py
djconnectwise/admin.py
djconnectwise/api.py
djconnectwise/apps.py
djconnectwise/callbacks.py
djconnectwise/models.py
djconnectwise/sync.py
djconnectwise/urls.py
djconnectwise/utils.py
djconnectwise/views.py
djconnectwise/__pycache__/__init__.cpython-38.pyc
djconnectwise/__pycache__/api.cpython-38.pyc
djconnectwise/__pycache__/apps.cpython-38.pyc
djconnectwise/__pycache__/callbacks.cpython-38.pyc
djconnectwise/__pycache__/models.cpython-38.pyc
djconnectwise/__pycache__/sync.cpython-38.pyc
djconnectwise/__pycache__/urls.cpython-38.pyc
djconnectwise/__pycache__/utils.cpython-38.pyc
djconnectwise/__pycache__/views.cpython-38.pyc
djconnectwise/management/__init__.py
djconnectwise/management/__pycache__/__init__.cpython-38.pyc
djconnectwise/management/commands/__init__.py
djconnectwise/management/commands/callbacks_deleted.py
djconnectwise/management/commands/callbacks_registered.py
djconnectwise/management/commands/cwclearoldsyncjobs.py
djconnectwise/management/commands/cwsync.py
djconnectwise/management/commands/list_callbacks.py
djconnectwise/management/commands/list_users.py
djconnectwise/management/commands/updateslaexpiretimes.py
djconnectwise/management/commands/__pycache__/__init__.cpython-38.pyc
djconnectwise/management/commands/__pycache__/cwsync.cpython-38.pyc
djconnectwise/management/commands/__pycache__/list_users.cpython-38.pyc
djconnectwise/migrations/0001_initial.py
djconnectwise/migrations/0002_auto_20170223_2143.py
djconnectwise/migrations/0003_auto_20170223_2233.py
djconnectwise/migrations/0004_auto_20170224_1853.py
djconnectwise/migrations/0005_auto_20170225_0101.py
djconnectwise/migrations/0006_auto_20170303_1242.py
djconnectwise/migrations/0007_auto_20170311_1415.py
djconnectwise/migrations/0008_project_status_name.py
djconnectwise/migrations/0009_member_license_class.py
djconnectwise/migrations/0010_remove_project_project_href.py
djconnectwise/migrations/0011_company_deleted_flag.py
django_connectwise-1.13.9.dist-info/LICENSE
django_connectwise-1.13.9.dist-info/METADATA
django_connectwise-1.13.9.dist-info/WHEEL
django_connectwise-1.13.9.dist-info/top_level.txt
django_connectwise-1.13.9.dist-info/RECORD
